README.md
setup.py
flaskbuckle/__init__.py
flaskbuckle/swagger-ui
flaskbuckle/swagger.py
flaskbuckle.egg-info/PKG-INFO
flaskbuckle.egg-info/SOURCES.txt
flaskbuckle.egg-info/dependency_links.txt
flaskbuckle.egg-info/requires.txt
flaskbuckle.egg-info/top_level.txt
flaskbuckle/swagger-ui/LICENSE
flaskbuckle/swagger-ui/index.html
flaskbuckle/swagger-ui/swagger-ui-bundle.js
flaskbuckle/swagger-ui/swagger-ui-bundle.js.map
flaskbuckle/swagger-ui/swagger-ui-standalone-preset.js
flaskbuckle/swagger-ui/swagger-ui-standalone-preset.js.map
flaskbuckle/swagger-ui/swagger-ui.css
flaskbuckle/swagger-ui/swagger-ui.css.map
flaskbuckle/swagger-ui/swagger-ui.js
flaskbuckle/swagger-ui/swagger-ui.js.map