Metadata-Version: 1.2
Name: flaskbuckle
Version: 0.1.6
Summary: Auto-generated Swagger specifications for your Flask API
Home-page: https://www.github.com/oscarnyl/flaskbuckle
Author: Oscar Nylander
Author-email: UNKNOWN
License: UNKNOWN
Platform: UNKNOWN
Requires-Python: >=3.6
